spreg/__init__.py
spreg/dgp.py
spreg/diagnostics.py
spreg/diagnostics_panel.py
spreg/diagnostics_probit.py
spreg/diagnostics_sp.py
spreg/diagnostics_sur.py
spreg/diagnostics_tsls.py
spreg/error_sp.py
spreg/error_sp_het.py
spreg/error_sp_het_regimes.py
spreg/error_sp_hom.py
spreg/error_sp_hom_regimes.py
spreg/error_sp_regimes.py
spreg/ml_error.py
spreg/ml_error_regimes.py
spreg/ml_lag.py
spreg/ml_lag_regimes.py
spreg/nslx.py
spreg/ols.py
spreg/ols_regimes.py
spreg/opt.py
spreg/optional_imports.ipynb
spreg/output.py
spreg/panel_fe.py
spreg/panel_re.py
spreg/panel_utils.py
spreg/probit.py
spreg/regimes.py
spreg/robust.py
spreg/skater_reg.py
spreg/sp_panels.py
spreg/spsearch.py
spreg/sputils.py
spreg/summary_output.py
spreg/summary_output.py.orig
spreg/sur.py
spreg/sur_error.py
spreg/sur_lag.py
spreg/sur_utils.py
spreg/twosls.py
spreg/twosls_regimes.py
spreg/twosls_sp.py
spreg/twosls_sp_regimes.py
spreg/user_output.py
spreg/utils.py
spreg/w_utils.py
spreg/tests/__init__.py
spreg/tests/skip.py
spreg/tests/test_diagnostics.py
spreg/tests/test_diagnostics_panel.py
spreg/tests/test_diagnostics_sp.py
spreg/tests/test_diagnostics_tsls.py
spreg/tests/test_error_sp.py
spreg/tests/test_error_sp_het.py
spreg/tests/test_error_sp_het_regimes.py
spreg/tests/test_error_sp_het_sparse.py
spreg/tests/test_error_sp_hom.py
spreg/tests/test_error_sp_hom_regimes.py
spreg/tests/test_error_sp_hom_sparse.py
spreg/tests/test_error_sp_regimes.py
spreg/tests/test_error_sp_sparse.py
spreg/tests/test_ml_error.py
spreg/tests/test_ml_error_regimes.py
spreg/tests/test_ml_lag.py
spreg/tests/test_ml_lag_regimes.py
spreg/tests/test_nslx.py
spreg/tests/test_ols.py
spreg/tests/test_ols_regimes.py
spreg/tests/test_ols_sparse.py
spreg/tests/test_panel_fe.py
spreg/tests/test_panel_re.py
spreg/tests/test_probit.py
spreg/tests/test_sp_panels.py
spreg/tests/test_spsearch.py
spreg/tests/test_sputils.py
spreg/tests/test_sur.py
spreg/tests/test_sur_error.py
spreg/tests/test_sur_lag.py
spreg/tests/test_twosls.py
spreg-1.8.4.dist-info/licenses/LICENSE.txt
spreg-1.8.4.dist-info/METADATA
spreg-1.8.4.dist-info/WHEEL
spreg-1.8.4.dist-info/top_level.txt
spreg-1.8.4.dist-info/RECORD
